falcon_morpheus_module/__init__.py
falcon_morpheus_module/dock_sftp_api.py
falcon_morpheus_module-0.0.13.dist-info/METADATA
falcon_morpheus_module-0.0.13.dist-info/WHEEL
falcon_morpheus_module-0.0.13.dist-info/RECORD
